[
 {
    "img_id":"gPpQNzQP6gE",
    "title":"Nadaniyan",
    "duration":"02:49",
    "channelName":"Akshath Acharya",
    "viewsCount":"5M",
    "likesCount":"328k"
 },
 {
    "img_id":"k3g_WjLCsXM",
    "title":"Sajni",
    "duration":"02:26",
    "channelName":"T-series",
    "viewsCount":"5M",
    "likesCount":"645k"
 },
 {
    "img_id":"7C2z4GqqS5E",
    "title":"Fakelove",
    "duration":"05:18",
    "channelName":"BTS",
    "viewsCount":"1.6B",
    "likesCount":"21M"
 },
 {
    "img_id":"XfC6xNwHi2Q",
    "title":"Ride it",
    "duration":"03:12",
    "channelName":"Cakes & Eclairs ",
    "viewsCount":"21M",
    "likesCount":"312k"
 },
 
 {
    "img_id":"lU-csIO1x0E",
    "title":"Until I Found You",
    "duration":"02:22",
    "channelName":"lyrics",
    "viewsCount":"12M",
    "likesCount":"109k"
 },
 {
    "img_id":"TUKyYfT_hNw",
    "title":" Wanna Be Yours",
    "duration":"05:18",
    "channelName":"lyrics",
    "viewsCount":"5.9M",
    "likesCount":"39k"
 },
 {
    "img_id":"gdZLi9oWNZg",
    "title":"Dynamite",
    "duration":"03:43",
    "channelName":"BTS",
    "viewsCount":"1.8B",
    "likesCount":"37M"
 },
 {
    "img_id":"XsX3ATc3FbA",
    "title":"Boy with luv",
    "duration":"04:12",
    "channelName":"BTS",
    "viewsCount":"1.7B",
    "likesCount":"28M"
 },
 {
    "img_id":"sEMfdtPgzOQ",
    "title":"Filter",
    "duration":"03:10",
    "channelName":"BTS",
    "viewsCount":"8.8M",
    "likesCount":"282k"
 },
 {
    "img_id":"MBdVXkSdhwU",
    "title":"DNA",
    "duration":"04:15",
    "channelName":"BTS",
    "viewsCount":"1.5B",
    "likesCount":"23M"
 },
 {
    "img_id":"pBuZEGYXA6E",
    "title":"Idol",
    "duration":"03:51",
    "channelName":"BTS",
    "viewsCount":"1.2B",
    "likesCount":"20M"
 },
 {
    "img_id":"__MIrmfbsmk",
    "title":"Home",
    "duration":"04:14",
    "channelName":"BTS",
    "viewsCount":"51M",
    "likesCount":"15M"
 }
]